{
  "width": 8,
  "height": 8,
  "budget": 20,
  "tileTypes":   [0,0,0,0,0,0,0,0,  0,1,1,1,1,1,0,0,  0,1,2,2,2,1,0,0,  0,1,2,3,2,1,0,0,  0,1,2,2,2,1,0,0,  0,1,1,1,1,1,0,0,  0,0,0,0,0,0,0,0,  0,0,0,0,0,0,0,0],
  "costData":    [1,1,1,1,1,1,1,1,  1,1,2,2,2,1,1,1,  1,2,3,3,3,2,1,1,  1,2,3,5,3,2,1,1,  1,2,3,3,3,2,1,1,  1,1,2,2,2,1,1,1,  1,1,1,1,1,1,1,1,  1,1,1,1,1,1,1,1],
  "ecoData1":    [0,0,0,0,0,0,0,0,  0,2,2,3,2,2,0,0,  0,2,3,4,3,2,0,0,  0,2,3,5,3,2,0,0,  0,2,3,4,3,2,0,0,  0,2,2,3,2,2,0,0,  0,0,0,0,0,0,0,0,  0,0,0,0,0,0,0,0],
  "lockedData":  [0,0,0,0,0,0,0,0,  0,0,0,1,0,0,0,0,  0,0,0,0,0,0,0,0,  0,0,0,0,0,0,0,0,  0,0,0,0,0,0,0,0,  0,0,0,0,0,0,0,0,  0,0,0,0,0,0,0,0,  0,0,0,0,0,0,0,0],
  "startCluster":[{"x":1,"y":2},{"x":1,"y":3}],
  "endCluster":  [{"x":6,"y":3},{"x":6,"y":4}]
}
